protocolx/__init__.py
protocolx/compose_protocol.py
protocolx/definition/type/protocol_sequence.py
protocolx/global_var/protocol_cache.py
protocolx-0.6.0.dist-info/METADATA
protocolx-0.6.0.dist-info/WHEEL
protocolx-0.6.0.dist-info/top_level.txt
protocolx-0.6.0.dist-info/RECORD
