Metadata-Version: 2.4
Name: protocolx
Version: 0.6.0
Summary: A type-safe protocol composition and runtime synthesis tool for Python, enabling plugin-based architectures and automatic protocol binding with full support for runtime checking, serialization, and IDE/type checker integration.
License-Expression: MIT
Project-URL: Homepage, https://github.com/jcfangc/protocolx.git
Project-URL: Repository, https://github.com/jcfangc/protocolx.git
Project-URL: Issues, https://github.com/jcfangc/protocolx/issues
Requires-Python: >=3.11
